[{"text": "lol", "value": 4605}, {"text": "man", "value": 2152}, {"text": "game", "value": 1764}, {"text": "like", "value": 1690}, {"text": "bro", "value": 1509}, {"text": "love", "value": 1354}, {"text": "now", "value": 1335}, {"text": "back", "value": 1188}, {"text": "time", "value": 1133}, {"text": "great", "value": 1118}, {"text": "thanks", "value": 1109}, {"text": "day", "value": 1027}, {"text": "see", "value": 966}, {"text": "new", "value": 914}, {"text": "right", "value": 888}, {"text": "know", "value": 833}, {"text": "yea", "value": 832}, {"text": "today", "value": 776}, {"text": "tonight", "value": 770}, {"text": "happy", "value": 761}, {"text": "kno", "value": 721}, {"text": "waldorfsfinest", "value": 709}, {"text": "way", "value": 694}, {"text": "thank", "value": 688}, {"text": "jus", "value": 688}, {"text": "win", "value": 678}, {"text": "com", "value": 677}, {"text": "play", "value": 661}, {"text": "congrats", "value": 649}, {"text": "best", "value": 638}, {"text": "wit", "value": 638}, {"text": "big", "value": 637}, {"text": "team", "value": 621}, {"text": "think", "value": 603}, {"text": "yall", "value": 583}, {"text": "going", "value": 573}, {"text": "keep", "value": 566}, {"text": "kingjames", "value": 566}, {"text": "check", "value": 559}, {"text": "need", "value": 544}]